Workbook

Sheet README
A1: Stakeholder + Outreach Intelligence System
A2: Purpose | B2: Track public-facing journalists/analysts covering foreign relations or India-related topics, prioritize outreach, manage pipeline activity, and reuse templates.
A3: Data date | B3: 2026-04-15
A4: Scope | B4: Council on Foreign Relations, New York Times, Wall Street Journal, Washington Post, Washington Examiner, FOX News, Associated Press, Bloomberg.
A5: Important | B5: Only clearly public or self-published contact details were included. Many journalists do not publish direct phone numbers; blanks should be treated as 'not publicly listed'.
A6: Sheets | B6: Journalist_Master, Pipeline, Dashboard, Narrative_Map, Messaging_Templates, Strategy_Playbook, Sources, Lists.
A8: Workflow
A9: 1) Filter Journalist_Master by publication, coverage focus, or priority score.
A10: 2) Use Contact Route + Confidence to decide whether to email, DM, or continue research.
A11: 3) Log every touch in Pipeline and set a follow-up due date.
A12: 4) Reuse subject lines and body copy from Messaging_Templates.
A13: 5) Use Narrative_Map and Strategy_Playbook to prepare spokespeople and supporting evidence.
A16: Scoring notes | B16: Priority Score is formula-driven from Influence + contactability + confidence + risk. Relationship Risk here means access difficulty / sensitivity, not editorial ideology.

Sheet Lists
A1: Analyst/Author | B1: High | C1: 1 | D1: Low | E1: New | F1: Intro email | G1: Prospect | H1: None
A2: Journalist | B2: Medium | C2: 2 | D2: Medium | E2: Engaged | F2: Monitor and build context | G2: Contacted | H2: Positive
A3: Commentary / Journalist | B3: Low | C3: 3 | D3: High | E3: Trusted | F3: Monitor and offer briefing | G3: Replied | H3: Neutral
C4: 4 | E4: Paused | F4: Offer data-led briefing | G4: Meeting | H4: Negative
C5: 5 | F5: Offer field reporting context | G5: Pitched
F6: Offer facts, timelines, and documentation | G6: Covered
F7: Use for Kashmir / strategic affairs context | G7: Paused
F8: Pitch only with strong defense/security peg
F9: Use for major conflict/foreign policy developments
F10: Use if opinion/security framing is relevant
F11: X follow / monitor
F12: Research / monitor

Sheet Journalist_Master
A1: ID | B1: Name | C1: Publication | D1: Stakeholder Type | E1: Role / Title | F1: Coverage Focus | G1: Geography | H1: Location | I1: Public Email | J1: Public Phone | K1: Alt/Public Contact | L1: X Handle | M1: Profile URL | N1: Contact Evidence URL | O1: Contact Confidence | P1: Influence Score | Q1: Relationship Risk | R1: Relationship Status | S1: Last Contact | T1: Next Action | U1: Contact Route | V1: Contact Coverage | W1: Priority Score | X1: Likely Angle | Y1: Notes | Z1: Last Verified
A2: 1 | B2: Alyssa Ayres | C2: Council on Foreign Relations | D2: Analyst/Author | E2: Adjunct Senior Fellow for India, Pakistan, and South Asia | F2: India, Pakistan, South Asia; trade and strategy | G2: South Asia | H2: Washington, DC | I2: alyssa@alyssaayres.com | K2: CFR profile + personal site email | L2: @AyresAlyssa | M2: https://www.cfr.org/experts/alyssa-ayres | N2: https://alyssaayres.com/contact/ | O2: High | P2: 4 | Q2: Low | R2: New | T2: Intro email | U2: =IF(I2<>"","Email",IF(L2<>"","X / social","Research")) | V2: =COUNTA(I2:L2) | W2: =ROUND(P2*2 + IF(O2="High",2,IF(O2="Medium",1,0)) + IF(I2<>"",2,0) + IF(L2<>"",1,0) - IF(Q2="High",1,0),0) | X2: India strategy / trade / South Asia | Y2: CFR analyst; useful for background briefings and expert context. | Z2: 2026-04-15
A3: 2 | B3: Manjari Chatterjee Miller | C3: Council on Foreign Relations | D3: Analyst/Author | E3: Senior Fellow | F3: India, China, and rising powers | G3: South Asia / Asia | H3: Toronto / CFR | I3: mmiller@cfr.org | M3: https://www.cfr.org/experts/manjari-chatterjee-miller | N3: https://www.cfr.org/experts/manjari-chatterjee-miller | O3: High | P3: 4 | Q3: Low | R3: New | T3: Intro email | U3: =IF(I3<>"","Email",IF(L3<>"","X / social","Research")) | V3: =COUNTA(I3:L3) | W3: =ROUND(P3*2 + IF(O3="High",2,IF(O3="Medium",1,0)) + IF(I3<>"",2,0) + IF(L3<>"",1,0) - IF(Q3="High",1,0),0) | X3: India-China / rising powers / foreign policy | Y3: Strong for geopolitics, rising powers, and India-China context. | Z3: 2026-04-15
A4: 3 | B4: Mujib Mashal | C4: The New York Times | D4: Journalist | E4: South Asia Bureau Chief | F4: South Asia, Afghanistan, India region | G4: South Asia | H4: New Delhi | L4: @MujMash | M4: https://muckrack.com/mujmash | N4: https://x.com/MujMash | O4: Medium | P4: 5 | Q4: Medium | R4: New | T4: Monitor and build context | U4: =IF(I4<>"","Email",IF(L4<>"","X / social","Research")) | V4: =COUNTA(I4:L4) | W4: =ROUND(P4*2 + IF(O4="High",2,IF(O4="Medium",1,0)) + IF(I4<>"",2,0) + IF(L4<>"",1,0) - IF(Q4="High",1,0),0) | X4: Regional politics / conflict / democracy | Y4: High-impact South Asia editor/correspondent. Public email not clearly self-published. | Z4: 2026-04-15
A5: 4 | B5: Anupreeta Das | C5: The New York Times | D5: Journalist | E5: South Asia Correspondent | F5: South Asia and India | G5: South Asia | H5: New Delhi / New York | L5: @PreetaTweets | M5: https://muckrack.com/preetatweets | N5: https://x.com/PreetaTweets | O5: Medium | P5: 4 | Q5: Medium | R5: New | T5: Monitor and offer briefing | U5: =IF(I5<>"","Email",IF(L5<>"","X / social","Research")) | V5: =COUNTA(I5:L5) | W5: =ROUND(P5*2 + IF(O5="High",2,IF(O5="Medium",1,0)) + IF(I5<>"",2,0) + IF(L5<>"",1,0) - IF(Q5="High",1,0),0) | X5: India politics / elites / explanatory features | Y5: Strong fit for India politics/business crossover. | Z5: 2026-04-15
A6: 5 | B6: Hari Kumar | C6: The New York Times | D6: Journalist | E6: Reporter, New Delhi | F6: India, politics, world | G6: India | H6: New Delhi | I6: kumar@nytimes.com | L6: @HariNYT | M6: https://muckrack.com/hari-kumar | N6: https://x.com/HariNYT | O6: High | P6: 4 | Q6: Medium | R6: New | T6: Intro email | U6: =IF(I6<>"","Email",IF(L6<>"","X / social","Research")) | V6: =COUNTA(I6:L6) | W6: =ROUND(P6*2 + IF(O6="High",2,IF(O6="Medium",1,0)) + IF(I6<>"",2,0) + IF(L6<>"",1,0) - IF(Q6="High",1,0),0) | X6: India politics / economy / breaking news | Y6: India-focused NYT reporter with public email in profile snippet. | Z6: 2026-04-15
A7: 6 | B7: Tripti Lahiri | C7: The Wall Street Journal | D7: Journalist | E7: South Asia Bureau Chief | F7: Business, politics, and technology across South Asia | G7: South Asia | H7: New Delhi | L7: @triptilahiri | M7: https://muckrack.com/tripti-lahiri | N7: https://x.com/triptilahiri | O7: Medium | P7: 5 | Q7: Medium | R7: New | T7: Offer data-led briefing | U7: =IF(I7<>"","Email",IF(L7<>"","X / social","Research")) | V7: =COUNTA(I7:L7) | W7: =ROUND(P7*2 + IF(O7="High",2,IF(O7="Medium",1,0)) + IF(I7<>"",2,0) + IF(L7<>"",1,0) - IF(Q7="High",1,0),0) | X7: India economy / geopolitics / enterprise | Y7: Prioritize for major India geopolitical/economic angles. | Z7: 2026-04-15
A8: 7 | B8: Shan Li | C8: The Wall Street Journal | D8: Journalist | E8: South Asia Correspondent | F8: India and the surrounding region | G8: South Asia | H8: New Delhi | L8: @ByShanLi | M8: https://muckrack.com/byshanli | N8: https://x.com/ByShanLi | O8: Medium | P8: 4 | Q8: Medium | R8: New | T8: Monitor and build context | U8: =IF(I8<>"","Email",IF(L8<>"","X / social","Research")) | V8: =COUNTA(I8:L8) | W8: =ROUND(P8*2 + IF(O8="High",2,IF(O8="Medium",1,0)) + IF(I8<>"",2,0) + IF(L8<>"",1,0) - IF(Q8="High",1,0),0) | X8: India region / business / cross-border issues | Y8: Good fit for India + cross-border business/policy stories. | Z8: 2026-04-15
A9: 8 | B9: Krishna Pokharel | C9: The Wall Street Journal | D9: Journalist | E9: Reporter | F9: Life, politics, business, environment, religion and culture in India and the Himalayan region | G9: India / Himalayas | H9: New Delhi | L9: @pokharelkrishna | M9: https://www.wsj.com/news/author/krishna-pokharel | N9: https://x.com/pokharelkrishna | O9: Medium | P9: 4 | Q9: Medium | R9: New | T9: Offer field reporting context | U9: =IF(I9<>"","Email",IF(L9<>"","X / social","Research")) | V9: =COUNTA(I9:L9) | W9: =ROUND(P9*2 + IF(O9="High",2,IF(O9="Medium",1,0)) + IF(I9<>"",2,0) + IF(L9<>"",1,0) - IF(Q9="High",1,0),0) | X9: India / Himalayas / society / environment | Y9: Useful for India/Himalayan region reporting and enterprise. | Z9: 2026-04-15
A10: 9 | B10: Pranshu Verma | C10: The Washington Post | D10: Journalist | E10: New Delhi Bureau Chief | F10: India, Bangladesh, Sri Lanka, Nepal and Bhutan | G10: South Asia | H10: New Delhi | I10: pranshu.verma@washpost.com | K10: Signal: pverma.10 | L10: @pranshuverma_ | M10: https://www.washingtonpost.com/people/pranshu-verma/ | N10: https://www.linkedin.com/posts/pranshuverma_as-of-today-i-can-start-reporting-on-india-activity-7358387673503334402-zXA2 | O10: High | P10: 5 | Q10: Medium | R10: New | T10: Intro email | U10: =IF(I10<>"","Email",IF(L10<>"","X / social","Research")) | V10: =COUNTA(I10:L10) | W10: =ROUND(P10*2 + IF(O10="High",2,IF(O10="Medium",1,0)) + IF(I10<>"",2,0) + IF(L10<>"",1,0) - IF(Q10="High",1,0),0) | X10: India and neighborhood / diplomacy / major news | Y10: Explicitly invited tips in public LinkedIn post. | Z10: 2026-04-15
A11: 10 | B11: Karishma Mehrotra | C11: The Washington Post | D11: Journalist | E11: South Asia Correspondent | F11: South Asia; tech, climate, society | G11: South Asia | H11: India | I11: karishma.mehrotra.7@gmail.com | L11: @karishma__m__ | M11: https://www.washingtonpost.com/people/karishma-mehrotra/ | N11: https://www.karishmamehrotra.com/contact | O11: High | P11: 4 | Q11: Medium | R11: New | T11: Intro email | U11: =IF(I11<>"","Email",IF(L11<>"","X / social","Research")) | V11: =COUNTA(I11:L11) | W11: =ROUND(P11*2 + IF(O11="High",2,IF(O11="Medium",1,0)) + IF(I11<>"",2,0) + IF(L11<>"",1,0) - IF(Q11="High",1,0),0) | X11: India society / tech / political reporting | Y11: Personal site publishes contact email; good fit for nuanced India narratives. | Z11: 2026-04-15
A12: 11 | B12: Joanna Slater | C12: The Washington Post | D12: Journalist | E12: National Correspondent; former India Bureau Chief | F12: Former India bureau chief; international reporting background | G12: U.S. / former South Asia | H12: United States | L12: @jslaternyc | M12: https://www.washingtonpost.com/people/joanna-slater/ | N12: https://x.com/jslaternyc | O12: Medium | P12: 4 | Q12: Medium | R12: New | T12: Monitor and maintain context | U12: =IF(I12<>"","Email",IF(L12<>"","X / social","Research")) | V12: =COUNTA(I12:L12) | W12: =ROUND(P12*2 + IF(O12="High",2,IF(O12="Medium",1,0)) + IF(I12<>"",2,0) + IF(L12<>"",1,0) - IF(Q12="High",1,0),0) | X12: Former India bureau chief / feature reporting | Y12: Relevant for former India relationships and broader WaPo network. | Z12: 2026-04-15
A13: 12 | B13: Timothy Nerozzi | C13: Washington Examiner | D13: Journalist | E13: Senior Foreign Affairs Reporter | F13: Global policy and diplomacy | G13: Global | H13: Washington, DC | L13: @TimothyNerozzi | M13: https://www.washingtonexaminer.com/author/timothy-nerozzi/ | N13: https://x.com/TimothyNerozzi | O13: Medium | P13: 3 | Q13: Medium | R13: New | T13: Offer security angle briefing | U13: =IF(I13<>"","Email",IF(L13<>"","X / social","Research")) | V13: =COUNTA(I13:L13) | W13: =ROUND(P13*2 + IF(O13="High",2,IF(O13="Medium",1,0)) + IF(I13<>"",2,0) + IF(L13<>"",1,0) - IF(Q13="High",1,0),0) | X13: Foreign affairs / diplomacy | Y13: Good fit for diplomacy or foreign policy hooks. | Z13: 2026-04-15
A14: 13 | B14: Brady Knox | C14: Washington Examiner | D14: Journalist | E14: Foreign Affairs Reporter | F14: Russia, Eastern Europe, foreign affairs | G14: Global | H14: Washington, DC | L14: @Brady_k6 | M14: https://www.washingtonexaminer.com/author/brady-knox/ | N14: https://x.com/Brady_k6 | O14: Medium | P14: 3 | Q14: Medium | R14: New | T14: Monitor and build relevance | U14: =IF(I14<>"","Email",IF(L14<>"","X / social","Research")) | V14: =COUNTA(I14:L14) | W14: =ROUND(P14*2 + IF(O14="High",2,IF(O14="Medium",1,0)) + IF(I14<>"",2,0) + IF(L14<>"",1,0) - IF(Q14="High",1,0),0) | X14: Foreign affairs / security | Y14: Best for geopolitical/security angles rather than domestic India stories. | Z14: 2026-04-15
A15: 14 | B15: Tom Rogan | C15: Washington Examiner | D15: Commentary / Journalist | E15: Commentary Writer | F15: Security and intelligence involving China, Russia, and the Middle East | G15: Global | H15: Washington, DC | I15: trogan@washingtonexaminer.com | K15: Encrypted: tjrogan@protonmail.com | L15: @TomRtweets | M15: https://www.washingtonexaminer.com/author/tom-rogan/ | N15: https://www.washingtonexaminer.com/author/tom-rogan/ | O15: High | P15: 4 | Q15: High | R15: New | T15: Use if opinion/security framing is relevant | U15: =IF(I15<>"","Email",IF(L15<>"","X / social","Research")) | V15: =COUNTA(I15:L15) | W15: =ROUND(P15*2 + IF(O15="High",2,IF(O15="Medium",1,0)) + IF(I15<>"",2,0) + IF(L15<>"",1,0) - IF(Q15="High",1,0),0) | X15: Security / China / Russia / Middle East | Y15: Opinion/commentary stakeholder; outreach should be tightly evidence-based. | Z15: 2026-04-15
A16: 15 | B16: Jennifer Griffin | C16: FOX News | D16: Journalist | E16: Chief National Security Correspondent | F16: National security, military, world | G16: Global / U.S. | H16: Washington, DC | L16: @JenGriffinFNC | M16: https://www.foxnews.com/person/g/jennifer-griffin | N16: https://x.com/JenGriffinFNC | O16: Medium | P16: 5 | Q16: High | R16: New | T16: Pitch only with strong defense/security peg | U16: =IF(I16<>"","Email",IF(L16<>"","X / social","Research")) | V16: =COUNTA(I16:L16) | W16: =ROUND(P16*2 + IF(O16="High",2,IF(O16="Medium",1,0)) + IF(I16<>"",2,0) + IF(L16<>"",1,0) - IF(Q16="High",1,0),0) | X16: National security / military / conflicts | Y16: Best for hard security, military, or crisis angles. | Z16: 2026-04-15
A17: 16 | B17: Trey Yingst | C17: FOX News | D17: Journalist | E17: Chief Foreign Correspondent | F17: World and conflict reporting | G17: Global | H17: International | L17: @TreyYingst | M17: https://muckrack.com/trey-yingst | N17: https://x.com/TreyYingst | O17: Medium | P17: 5 | Q17: High | R17: New | T17: Use for major conflict/foreign policy developments | U17: =IF(I17<>"","Email",IF(L17<>"","X / social","Research")) | V17: =COUNTA(I17:L17) | W17: =ROUND(P17*2 + IF(O17="High",2,IF(O17="Medium",1,0)) + IF(I17<>"",2,0) + IF(L17<>"",1,0) - IF(Q17="High",1,0),0) | X17: War / conflict / foreign desk | Y17: Broadcast-first foreign correspondent; prioritize only for big breaking hooks. | Z17: 2026-04-15
A18: 17 | B18: Sheikh Saaliq | C18: Associated Press | D18: Journalist | E18: India Reporter / South Asia Correspondent | F18: Politics, democracy, conflict and religion across India and South Asia | G18: India / South Asia | H18: New Delhi | L18: @Sheikh_Saaliq | M18: https://apnews.com/author/sheikh-saaliq | N18: https://x.com/Sheikh_Saaliq | O18: Medium | P18: 4 | Q18: Medium | R18: New | T18: Offer facts, timelines, and documentation | U18: =IF(I18<>"","Email",IF(L18<>"","X / social","Research")) | V18: =COUNTA(I18:L18) | W18: =ROUND(P18*2 + IF(O18="High",2,IF(O18="Medium",1,0)) + IF(I18<>"",2,0) + IF(L18<>"",1,0) - IF(Q18="High",1,0),0) | X18: India politics / conflict / religion / AP wire | Y18: AP wire reach makes him high leverage despite limited public contact details. | Z18: 2026-04-15
A19: 18 | B19: Sibi Arasu | C19: Associated Press | D19: Journalist | E19: Climate Journalist | F19: Climate change from India and South Asia | G19: India / South Asia | H19: India | I19: sarasu@ap.org | L19: @sibi123 | M19: https://apnews.com/author/sibi-arasu | N19: https://x.com/sibi123 | O19: High | P19: 4 | Q19: Low | R19: New | T19: Intro email with data-heavy climate/energy angle | U19: =IF(I19<>"","Email",IF(L19<>"","X / social","Research")) | V19: =COUNTA(I19:L19) | W19: =ROUND(P19*2 + IF(O19="High",2,IF(O19="Medium",1,0)) + IF(I19<>"",2,0) + IF(L19<>"",1,0) - IF(Q19="High",1,0),0) | X19: Climate / energy transition / India | Y19: Public email self-listed in X/Muck Rack snippet. | Z19: 2026-04-15
A20: 19 | B20: Aijaz Hussain | C20: Associated Press | D20: Journalist | E20: India Reporter | F20: Kashmir conflict, Indian politics and strategic affairs, and climate | G20: India / Kashmir | H20: India | L20: @hussain_aijaz | M20: https://apnews.com/author/aijaz-hussain | N20: https://x.com/hussain_aijaz | O20: Medium | P20: 4 | Q20: Medium | R20: New | T20: Use for Kashmir / strategic affairs context | U20: =IF(I20<>"","Email",IF(L20<>"","X / social","Research")) | V20: =COUNTA(I20:L20) | W20: =ROUND(P20*2 + IF(O20="High",2,IF(O20="Medium",1,0)) + IF(I20<>"",2,0) + IF(L20<>"",1,0) - IF(Q20="High",1,0),0) | X20: Kashmir / strategic affairs / AP wire | Y20: Strong AP contact for Kashmir and strategic affairs. | Z20: 2026-04-15
A21: 20 | B21: Swati Gupta | C21: Bloomberg | D21: Journalist | E21: South Asia Political Reporter | F21: South Asia politics | G21: South Asia | H21: India | I21: sgupta1048@bloomberg.net | L21: @sw_gs | M21: https://www.bloomberg.com/authors/AWZfRQwLDfI/swati-gupta | N21: https://x.com/sw_gs | O21: High | P21: 4 | Q21: Low | R21: New | T21: Intro email | U21: =IF(I21<>"","Email",IF(L21<>"","X / social","Research")) | V21: =COUNTA(I21:L21) | W21: =ROUND(P21*2 + IF(O21="High",2,IF(O21="Medium",1,0)) + IF(I21<>"",2,0) + IF(L21<>"",1,0) - IF(Q21="High",1,0),0) | X21: South Asia politics / regulation | Y21: Good for India politics/regulatory angles. | Z21: 2026-04-15
A22: 21 | B22: Rajesh Kumar Singh | C22: Bloomberg | D22: Journalist | E22: Reporter | F22: India energy and commodities | G22: India | H22: New Delhi | I22: rsingh133@bloomberg.net | L22: @rajeshsing13 | M22: https://www.bloomberg.com/authors/AQMyDU0Qjbo/rajesh-kumar-singh | N22: https://news.bloomberglaw.com/author/rajesh-kumar-singh-16986637 | O22: High | P22: 4 | Q22: Low | R22: New | T22: Intro email with market/energy hook | U22: =IF(I22<>"","Email",IF(L22<>"","X / social","Research")) | V22: =COUNTA(I22:L22) | W22: =ROUND(P22*2 + IF(O22="High",2,IF(O22="Medium",1,0)) + IF(I22<>"",2,0) + IF(L22<>"",1,0) - IF(Q22="High",1,0),0) | X22: Energy / commodities / policy / India | Y22: Public Bloomberg law author page includes direct email. | Z22: 2026-04-15
A23: 22 | B23: Advait Palepu | C23: Bloomberg | D23: Journalist | E23: India Wealth Reporter | F23: India wealth, capital flows, tax and policy | G23: India | H23: India | I23: advait.prx@protonmail.me | L23: @advait_px | M23: https://www.bloomberg.com/authors/AWRasSKfZpM/advait-palepu | N23: https://x.com/advait_px | O23: High | P23: 3 | Q23: Low | R23: New | T23: Intro email with markets angle | U23: =IF(I23<>"","Email",IF(L23<>"","X / social","Research")) | V23: =COUNTA(I23:L23) | W23: =ROUND(P23*2 + IF(O23="High",2,IF(O23="Medium",1,0)) + IF(I23<>"",2,0) + IF(L23<>"",1,0) - IF(Q23="High",1,0),0) | X23: Wealth / tax / global capital / India | Y23: Tip email is self-published in X profile snippet. | Z23: 2026-04-15

Sheet Pipeline
A1: ID | B1: Name | C1: Publication | D1: Priority Score | E1: Stage | F1: Last Action | G1: Follow-Up Due | H1: Days to Follow-Up | I1: Response | J1: Outcome | K1: Owner | L1: Notes
A2: =Journalist_Master!A2 | B2: =Journalist_Master!B2 | C2: =Journalist_Master!C2 | D2: =Journalist_Master!W2 | E2: Prospect | H2: =IF(G2="","",G2-TODAY()) | I2: None
A3: =Journalist_Master!A3 | B3: =Journalist_Master!B3 | C3: =Journalist_Master!C3 | D3: =Journalist_Master!W3 | E3: Prospect | H3: =IF(G3="","",G3-TODAY()) | I3: None
A4: =Journalist_Master!A4 | B4: =Journalist_Master!B4 | C4: =Journalist_Master!C4 | D4: =Journalist_Master!W4 | E4: Prospect | H4: =IF(G4="","",G4-TODAY()) | I4: None
A5: =Journalist_Master!A5 | B5: =Journalist_Master!B5 | C5: =Journalist_Master!C5 | D5: =Journalist_Master!W5 | E5: Prospect | H5: =IF(G5="","",G5-TODAY()) | I5: None
A6: =Journalist_Master!A6 | B6: =Journalist_Master!B6 | C6: =Journalist_Master!C6 | D6: =Journalist_Master!W6 | E6: Prospect | H6: =IF(G6="","",G6-TODAY()) | I6: None
A7: =Journalist_Master!A7 | B7: =Journalist_Master!B7 | C7: =Journalist_Master!C7 | D7: =Journalist_Master!W7 | E7: Prospect | H7: =IF(G7="","",G7-TODAY()) | I7: None
A8: =Journalist_Master!A8 | B8: =Journalist_Master!B8 | C8: =Journalist_Master!C8 | D8: =Journalist_Master!W8 | E8: Prospect | H8: =IF(G8="","",G8-TODAY()) | I8: None
A9: =Journalist_Master!A9 | B9: =Journalist_Master!B9 | C9: =Journalist_Master!C9 | D9: =Journalist_Master!W9 | E9: Prospect | H9: =IF(G9="","",G9-TODAY()) | I9: None
A10: =Journalist_Master!A10 | B10: =Journalist_Master!B10 | C10: =Journalist_Master!C10 | D10: =Journalist_Master!W10 | E10: Prospect | H10: =IF(G10="","",G10-TODAY()) | I10: None
A11: =Journalist_Master!A11 | B11: =Journalist_Master!B11 | C11: =Journalist_Master!C11 | D11: =Journalist_Master!W11 | E11: Prospect | H11: =IF(G11="","",G11-TODAY()) | I11: None
A12: =Journalist_Master!A12 | B12: =Journalist_Master!B12 | C12: =Journalist_Master!C12 | D12: =Journalist_Master!W12 | E12: Prospect | H12: =IF(G12="","",G12-TODAY()) | I12: None
A13: =Journalist_Master!A13 | B13: =Journalist_Master!B13 | C13: =Journalist_Master!C13 | D13: =Journalist_Master!W13 | E13: Prospect | H13: =IF(G13="","",G13-TODAY()) | I13: None
... A23: =Journalist_Master!A23 | B23: =Journalist_Master!B23 | C23: =Journalist_Master!C23 | D23: =Journalist_Master!W23 | E23: Prospect | H23: =IF(G23="","",G23-TODAY()) | I23: None

Sheet Dashboard
A1: Outreach Dashboard
A3: Metric | B3: Value | D3: Publication | E3: Count | F3: Avg Influence
A4: Total stakeholders | B4: =COUNTA(Journalist_Master!B2:B23) | D4: Council on Foreign Relations | E4: =COUNTIF(Journalist_Master!C2:C23,D4) | F4: =ROUND(AVERAGEIF(Journalist_Master!C2:C23,D4,Journalist_Master!P2:P23),1)
A5: Public emails listed | B5: =COUNTIF(Journalist_Master!I2:I23,"?*") | D5: The New York Times | E5: =COUNTIF(Journalist_Master!C2:C23,D5) | F5: =ROUND(AVERAGEIF(Journalist_Master!C2:C23,D5,Journalist_Master!P2:P23),1)
A6: X handles listed | B6: =COUNTIF(Journalist_Master!L2:L23,"@*") | D6: The Wall Street Journal | E6: =COUNTIF(Journalist_Master!C2:C23,D6) | F6: =ROUND(AVERAGEIF(Journalist_Master!C2:C23,D6,Journalist_Master!P2:P23),1)
A7: High-confidence contacts | B7: =COUNTIF(Journalist_Master!O2:O23,"High") | D7: The Washington Post | E7: =COUNTIF(Journalist_Master!C2:C23,D7) | F7: =ROUND(AVERAGEIF(Journalist_Master!C2:C23,D7,Journalist_Master!P2:P23),1)
A8: Average influence | B8: =ROUND(AVERAGE(Journalist_Master!P2:P23),1) | D8: Washington Examiner | E8: =COUNTIF(Journalist_Master!C2:C23,D8) | F8: =ROUND(AVERAGEIF(Journalist_Master!C2:C23,D8,Journalist_Master!P2:P23),1)
A9: Avg priority score | B9: =ROUND(AVERAGE(Journalist_Master!W2:W23),1) | D9: FOX News | E9: =COUNTIF(Journalist_Master!C2:C23,D9) | F9: =ROUND(AVERAGEIF(Journalist_Master!C2:C23,D9,Journalist_Master!P2:P23),1)
D10: Associated Press | E10: =COUNTIF(Journalist_Master!C2:C23,D10) | F10: =ROUND(AVERAGEIF(Journalist_Master!C2:C23,D10,Journalist_Master!P2:P23),1)
D11: Bloomberg | E11: =COUNTIF(Journalist_Master!C2:C23,D11) | F11: =ROUND(AVERAGEIF(Journalist_Master!C2:C23,D11,Journalist_Master!P2:P23),1)
D14: Pipeline Stage | E14: Count
D15: Prospect | E15: =COUNTIF(Pipeline!E2:E23,D15)
D16: Contacted | E16: =COUNTIF(Pipeline!E2:E23,D16)
D17: Replied | E17: =COUNTIF(Pipeline!E2:E23,D17)
D18: Meeting | E18: =COUNTIF(Pipeline!E2:E23,D18)
D19: Pitched | E19: =COUNTIF(Pipeline!E2:E23,D19)
D20: Covered | E20: =COUNTIF(Pipeline!E2:E23,D20)
D21: Paused | E21: =COUNTIF(Pipeline!E2:E23,D21)

Sheet Narrative_Map
A1: Narrative Theme | B1: Likely Editorial Angle | C1: Evidence / Proof Points to Prepare | D1: Watchouts | E1: Best Targets | F1: Suggested Spokesperson Type | G1: Status
A2: U.S.-India trade and tariffs | B2: How bilateral tensions affect markets, supply chains, and diplomacy | C2: Trade numbers, announced agreements, tariff timelines, business impact examples | D2: Avoid vague 'historic' claims without dates or figures | E2: WSJ, Bloomberg, NYT, WaPo | F2: Trade or policy spokesperson | G2: Ready
A3: India's strategic autonomy | B3: Why India balances the U.S., Russia, and regional interests | C3: Specific voting records, procurement facts, official statements, timeline context | D3: Do not overstate alliance language | E3: CFR, WaPo, WSJ, Fox | F3: Foreign policy expert | G3: Ready
A4: China / Indo-Pacific security | B4: Regional deterrence, maritime security, defense cooperation | C4: Exercises, defense deals, Indo-Pacific framing, allied quotes | D4: Avoid speculative military claims | E4: Fox, Examiner, CFR, WaPo | F4: Defense / security spokesperson | G4: Ready
A5: Democracy and rights scrutiny | B5: Questions on institutions, civil liberties, or social cohesion | C5: Court rulings, election data, public policy specifics, third-party reports | D5: Do not attack reporters; stay evidence-led | E5: NYT, WaPo, AP | F5: Legal / governance spokesperson | G5: Needs source pack
A6: Climate and energy transition | B6: Coal, renewables, grid demand, financing, energy security | C6: Capacity numbers, targets, emissions context, transition constraints | D6: Avoid greenwashing language | E6: Bloomberg, AP, WSJ | F6: Climate / energy expert | G6: Ready
A7: Kashmir and regional security | B7: Conflict, sovereignty, militancy, civilian impact | C7: Precise timelines, casualty sourcing, official positions, map accuracy | D7: High sensitivity; check wording carefully | E7: AP, NYT, WaPo, CFR | F7: Regional security expert | G7: High sensitivity
A8: Technology, regulation, and AI | B8: Data governance, platform rules, semiconductor or AI policy | C8: Law text, regulator statements, startup/industry examples | D8: Avoid abstract policy language without use cases | E8: WaPo, Bloomberg, NYT | F8: Tech policy spokesperson | G8: Ready
A9: Capital flows and elite wealth | B9: Billionaires, tax policy, foreign capital, wealth migration | C9: Market data, policy changes, affected sectors, quotes from filings | D9: Avoid unsupported motives | E9: Bloomberg, WSJ, NYT | F9: Economics / finance spokesperson | G9: Ready

Sheet Messaging_Templates
A1: Template ID | B1: Use Case | C1: Subject Line | D1: Body
A2: T1 | B2: Warm intro / background briefing | C2: Background note on [topic] + available source/briefing | D2: Hi [Name], Sharing a short background note on [topic] in case it's useful for your coverage. I can also connect you with [expert/spokesperson] for a quick on-background conversation or send supporting documents/data points. Best, [Your Name]
A3: T2 | B3: Data-led India policy pitch | C3: Quick context on [policy/development] in India | D3: Hi [Name], Thought this may be relevant to your [India/foreign policy/business] beat. We pulled together a concise evidence pack on [topic] with dates, data points, and source documents. Happy to send that over or arrange a short call. Best, [Your Name]
A4: T3 | B4: Security / defense angle | C4: Source offer: [topic] and its security implications | D4: Hi [Name], If helpful, we can provide a fast-turn backgrounder on [topic], including the security implications, timeline, and what to watch next. We can also arrange a quote from [expert name/title]. Best, [Your Name]
A5: T4 | B5: Follow-up after no reply | C5: Following up on [topic] | D5: Hi [Name], Just following up in case the earlier note got buried. If this angle is useful, I can send a tighter one-page summary or a short bullet list tailored to your beat. Best, [Your Name]
A6: T5 | B6: Corrective / context note | C6: Additional context on [recent coverage topic] | D6: Hi [Name], I read your recent piece and wanted to share a few points of context that may be useful for any follow-on reporting. I've kept them factual and source-backed below. Happy to send the underlying documents if helpful. Best, [Your Name]

Sheet Strategy_Playbook
A1: Strategy Playbook
A3: Section | B3: Guidance
A4: 1. Segment outlets by what they care about | B4: CFR and WaPo/NYT often need strong context and sourcing; WSJ/Bloomberg respond well to economic/geopolitical hooks; AP values crisp facts and verification; Fox/Examiner often respond best to security, diplomacy, and hard-news pegs.
A5: 2. Match the journalist to the angle | B5: Use the 'Likely Angle' column before any outreach. Keep the pitch narrow: one story, one news hook, one reason it matters now.
A6: 3. Use public-contact hierarchy | B6: Use direct public email first when clearly listed. If there is no public email, prefer X/social or continued monitoring over guessing contact details.
A7: 4. Prep a source pack | B7: Have dates, data, original documents, quoteable experts, and a one-line why-now ready before outreach.
A8: 5. Follow-up discipline | B8: One initial message + one concise follow-up is usually enough. Log everything in Pipeline and stop if the contact appears uninterested.
A9: 6. High-sensitivity topics | B9: For Kashmir, rights, religion, or conflict, route through a subject-matter expert and verify every timeline/date before sending.
A10: 7. Broadcast targets | B10: For TV correspondents, pitch only when the story has a crisp security/conflict peg or a strong visual/news value.

Sheet Sources
A1: ID | B1: Name | C1: Publication | D1: Profile / role URL | E1: Contact evidence URL | F1: Verification note
A2: 1 | B2: Alyssa Ayres | C2: Council on Foreign Relations | D2: https://www.cfr.org/experts/alyssa-ayres | E2: https://alyssaayres.com/contact/ | F2: Official or self-published contact detail
A3: 2 | B3: Manjari Chatterjee Miller | C3: Council on Foreign Relations | D3: https://www.cfr.org/experts/manjari-chatterjee-miller | E3: https://www.cfr.org/experts/manjari-chatterjee-miller | F3: Official or self-published contact detail
A4: 3 | B4: Mujib Mashal | C4: The New York Times | D4: https://muckrack.com/mujmash | E4: https://x.com/MujMash | F4: Role/handle verified; no clear self-published direct email
A5: 4 | B5: Anupreeta Das | C5: The New York Times | D5: https://muckrack.com/preetatweets | E5: https://x.com/PreetaTweets | F5: Role/handle verified; no clear self-published direct email
A6: 5 | B6: Hari Kumar | C6: The New York Times | D6: https://muckrack.com/hari-kumar | E6: https://x.com/HariNYT | F6: Official or self-published contact detail
A7: 6 | B7: Tripti Lahiri | C7: The Wall Street Journal | D7: https://muckrack.com/tripti-lahiri | E7: https://x.com/triptilahiri | F7: Role/handle verified; no clear self-published direct email
A8: 7 | B8: Shan Li | C8: The Wall Street Journal | D8: https://muckrack.com/byshanli | E8: https://x.com/ByShanLi | F8: Role/handle verified; no clear self-published direct email
A9: 8 | B9: Krishna Pokharel | C9: The Wall Street Journal | D9: https://www.wsj.com/news/author/krishna-pokharel | E9: https://x.com/pokharelkrishna | F9: Role/handle verified; no clear self-published direct email
A10: 9 | B10: Pranshu Verma | C10: The Washington Post | D10: https://www.washingtonpost.com/people/pranshu-verma/ | E10: https://www.linkedin.com/posts/pranshuverma_as-of-today-i-can-start-reporting-on-india-activity-7358387673503334402-zXA2 | F10: Official or self-published contact detail
A11: 10 | B11: Karishma Mehrotra | C11: The Washington Post | D11: https://www.washingtonpost.com/people/karishma-mehrotra/ | E11: https://www.karishmamehrotra.com/contact | F11: Official or self-published contact detail
A12: 11 | B12: Joanna Slater | C12: The Washington Post | D12: https://www.washingtonpost.com/people/joanna-slater/ | E12: https://x.com/jslaternyc | F12: Role/handle verified; no clear self-published direct email
A13: 12 | B13: Timothy Nerozzi | C13: Washington Examiner | D13: https://www.washingtonexaminer.com/author/timothy-nerozzi/ | E13: https://x.com/TimothyNerozzi | F13: Role/handle verified; no clear self-published direct email
... A23: 22 | B23: Advait Palepu | C23: Bloomberg | D23: https://www.bloomberg.com/authors/AWRasSKfZpM/advait-palepu | E23: https://x.com/advait_px | F23: Official or self-published contact detail
